{"adPreferences":{"filtered_ads":[],"filtered_categories":[],"saved_ads":[],"flagged_ads":[]},"adsShownHistory":[{"timestamp_in_seconds":1609649547,"ad_content":{"type":"ad_notification","uuid":"ea171a3a-a965-4b4a-bd3e-f977bf263fe9","creative_instance_id":"a8bd7888-e394-41e3-9157-aff7ea64b524","creative_set_id":"7c53c541-1be6-4e1d-8af7-768ec6484f07","campaign_id":"a57837b5-77b0-40c1-98ec-332b96ac6a29","brand":"Gemini - Bitcoin Is Up 130%","brand_info":"Build your crypto empire with Gemini!","brand_logo":"","brand_display_url":"getstarted.gemini.com","brand_url":"https://getstarted.gemini.com/time-for-crypto/","like_action":0,"ad_action":"dismiss","saved_ad":false,"flagged_ad":false},"category_content":{"category":"hobbies & interests","opt_action":0}},{"timestamp_in_seconds":1609649533,"ad_content":{"type":"ad_notification","uuid":"ea171a3a-a965-4b4a-bd3e-f977bf263fe9","creative_instance_id":"a8bd7888-e394-41e3-9157-aff7ea64b524","creative_set_id":"7c53c541-1be6-4e1d-8af7-768ec6484f07","campaign_id":"a57837b5-77b0-40c1-98ec-332b96ac6a29","brand":"Gemini - Bitcoin Is Up 130%","brand_info":"Build your crypto empire with Gemini!","brand_logo":"","brand_display_url":"getstarted.gemini.com","brand_url":"https://getstarted.gemini.com/time-for-crypto/","like_action":0,"ad_action":"view","saved_ad":false,"flagged_ad":false},"category_content":{"category":"hobbies & interests","opt_action":0}}],"purchaseIntentSignalHistory":{},"adsUUIDSeen":{"a8bd7888-e394-41e3-9157-aff7ea64b524":1},"advertisersUUIDSeen":{"36e875d1-5f09-4caa-a762-c7d87adbef39":1},"nextCheckServeAd":0,"pageProbabilitiesHistory":[{"pageProbabilities":[{"category":"architecture-architecture","pageScore":0.00996939092874527},{"category":"arts & entertainment-animation","pageScore":0.010048829950392247},{"category":"arts & entertainment-anime","pageScore":0.007510652765631676},{"category":"arts & entertainment-arts & entertainment","pageScore":0.0074151139706373219},{"category":"arts & entertainment-comics","pageScore":0.009184656664729119},{"category":"arts & entertainment-television","pageScore":0.0334656722843647},{"category":"automotive-automotive","pageScore":0.006966523360460997},{"category":"automotive-pickup trucks","pageScore":0.0072288960218429569},{"category":"business-energy","pageScore":0.007454459089785814},{"category":"business-marketing","pageScore":0.009365910664200783},{"category":"crypto-crypto","pageScore":0.010979474522173405},{"category":"education-education","pageScore":0.008750890381634236},{"category":"family & parenting-pregnancy","pageScore":0.007932297885417939},{"category":"fashion-fashion","pageScore":0.0075846342369914059},{"category":"food & drink-cooking","pageScore":0.008559954352676869},{"category":"food & drink-vegetarian","pageScore":0.015720587223768235},{"category":"health & fitness-alternative medicine","pageScore":0.009213927201926709},{"category":"health & fitness-exercise","pageScore":0.010218731127679348},{"category":"hobbies & interests-horse racing","pageScore":0.007335578557103872},{"category":"hobbies & interests-photography","pageScore":0.01805073954164982},{"category":"hobbies & interests-writing","pageScore":0.007885465398430825},{"category":"home-appliances","pageScore":0.013246271759271622},{"category":"home-home","pageScore":0.008127368986606598},{"category":"military-military","pageScore":0.0068585132248699669},{"category":"personal finance-insurance","pageScore":0.010553413070738316},{"category":"personal finance-personal finance","pageScore":0.011570175178349018},{"category":"personal finance-tax","pageScore":0.007122882641851902},{"category":"real estate-real estate","pageScore":0.007180186454206705},{"category":"science-astronomy","pageScore":0.007587917149066925},{"category":"science-geography","pageScore":0.00790622178465128},{"category":"science-mathematics","pageScore":0.00944903027266264},{"category":"science-palaeontology","pageScore":0.006716158241033554},{"category":"science-science","pageScore":0.00791245698928833},{"category":"sports-baseball","pageScore":0.00784457940608263},{"category":"sports-climbing","pageScore":0.007828101515769959},{"category":"sports-jogging","pageScore":0.008633780293166638},{"category":"sports-martial arts","pageScore":0.008512663654983044},{"category":"sports-olympics","pageScore":0.007540611084550619},{"category":"sports-skiing","pageScore":0.008213485591113568},{"category":"sports-snowboarding","pageScore":0.006759349722415209},{"category":"sports-tennis","pageScore":0.006961190607398748},{"category":"technology & computing-apple","pageScore":0.010019907727837563},{"category":"technology & computing-database","pageScore":0.007729953154921532},{"category":"technology & computing-freeware","pageScore":0.007391940802335739},{"category":"technology & computing-programming","pageScore":0.006827395409345627},{"category":"technology & computing-software","pageScore":0.009732612408697605},{"category":"technology & computing-technology & computing","pageScore":0.01689954660832882},{"category":"technology & computing-windows","pageScore":0.007770264986902475}]},{"pageProbabilities":[{"category":"architecture-architecture","pageScore":0.009573456831276417},{"category":"arts & entertainment-animation","pageScore":0.008334847167134285},{"category":"arts & entertainment-anime","pageScore":0.0071278889663517479},{"category":"arts & entertainment-arts & entertainment","pageScore":0.006981327664107084},{"category":"arts & entertainment-comics","pageScore":0.011774455197155476},{"category":"arts & entertainment-television","pageScore":0.03894174098968506},{"category":"automotive-automotive","pageScore":0.008205169811844826},{"category":"automotive-pickup trucks","pageScore":0.006905900314450264},{"category":"business-energy","pageScore":0.007881496101617813},{"category":"business-marketing","pageScore":0.008604465052485466},{"category":"crypto-crypto","pageScore":0.009370976127684117},{"category":"education-education","pageScore":0.009518438018858433},{"category":"family & parenting-pregnancy","pageScore":0.007834270596504212},{"category":"food & drink-cider","pageScore":0.006818453315645456},{"category":"food & drink-cooking","pageScore":0.008798508904874325},{"category":"food & drink-vegetarian","pageScore":0.013452707789838314},{"category":"health & fitness-alternative medicine","pageScore":0.010057481937110424},{"category":"health & fitness-exercise","pageScore":0.010092613287270069},{"category":"hobbies & interests-needlework","pageScore":0.006738454103469849},{"category":"hobbies & interests-photography","pageScore":0.011483719572424889},{"category":"hobbies & interests-writing","pageScore":0.008199990727007389},{"category":"home-appliances","pageScore":0.012377992272377015},{"category":"home-home","pageScore":0.008410821668803692},{"category":"military-military","pageScore":0.006865379866212606},{"category":"personal finance-insurance","pageScore":0.009307974018156529},{"category":"personal finance-investing","pageScore":0.008053428493440152},{"category":"personal finance-personal finance","pageScore":0.011330884881317616},{"category":"pets-cats","pageScore":0.0068782321177423},{"category":"pets-pets","pageScore":0.007882175967097283},{"category":"science-chemistry","pageScore":0.007200668100267649},{"category":"science-geography","pageScore":0.00794396735727787},{"category":"science-mathematics","pageScore":0.007872222922742367},{"category":"science-physics","pageScore":0.007009499240666628},{"category":"science-science","pageScore":0.008044460788369179},{"category":"sports-american football","pageScore":0.0077828108333051209},{"category":"sports-baseball","pageScore":0.00795646384358406},{"category":"sports-basketball","pageScore":0.007053646259009838},{"category":"sports-boxing","pageScore":0.007164642680436373},{"category":"sports-climbing","pageScore":0.0074416701681911949},{"category":"sports-hunting","pageScore":0.007006034720689058},{"category":"sports-jogging","pageScore":0.007662069983780384},{"category":"sports-martial arts","pageScore":0.008529474958777428},{"category":"sports-olympics","pageScore":0.007556024007499218},{"category":"sports-snowboarding","pageScore":0.007097653578966856},{"category":"sports-swimming","pageScore":0.007540152873843908},{"category":"sports-tennis","pageScore":0.007165015209466219},{"category":"technology & computing-apple","pageScore":0.009222541004419327},{"category":"technology & computing-database","pageScore":0.008229273371398449},{"category":"technology & computing-freeware","pageScore":0.007180886808782816},{"category":"technology & computing-programming","pageScore":0.009556927718222142},{"category":"technology & computing-software","pageScore":0.0074400645680725578},{"category":"technology & computing-technology & computing","pageScore":0.009455901570618153},{"category":"technology & computing-unix","pageScore":0.007653418928384781},{"category":"travel-adventure travel","pageScore":0.006783577147871256}]},{"pageProbabilities":[{"category":"architecture-architecture","pageScore":0.007827917113900185},{"category":"arts & entertainment-anime","pageScore":0.010120579972863198},{"category":"arts & entertainment-design","pageScore":0.010076944716274739},{"category":"arts & entertainment-film","pageScore":0.008105075918138028},{"category":"arts & entertainment-radio","pageScore":0.008296780288219452},{"category":"automotive-pickup trucks","pageScore":0.007082324009388685},{"category":"business-business","pageScore":0.009266632609069348},{"category":"business-energy","pageScore":0.007907257415354252},{"category":"business-marketing","pageScore":0.006825024727731943},{"category":"cell phones-cell phones","pageScore":0.007467710878700018},{"category":"education-education","pageScore":0.008089023642241955},{"category":"education-homeschooling","pageScore":0.007027884479612112},{"category":"fashion-clothing","pageScore":0.006928169168531895},{"category":"folklore-paranormal phenomena","pageScore":0.006786610931158066},{"category":"food & drink-vegan","pageScore":0.009246491827070713},{"category":"health & fitness-alternative medicine","pageScore":0.008848587982356549},{"category":"health & fitness-exercise","pageScore":0.007536536082625389},{"category":"history-history","pageScore":0.008501403033733368},{"category":"hobbies & interests-coins","pageScore":0.00847654975950718},{"category":"hobbies & interests-photography","pageScore":0.007202913053333759},{"category":"hobbies & interests-sci-fi","pageScore":0.01991928741335869},{"category":"hobbies & interests-scouting","pageScore":0.007846119813621045},{"category":"home-garden","pageScore":0.008623798377811909},{"category":"home-home","pageScore":0.00789952278137207},{"category":"home-interior design","pageScore":0.010293501429259777},{"category":"military-military","pageScore":0.007976816035807133},{"category":"personal finance-credit & debt & loans","pageScore":0.010029331780970097},{"category":"personal finance-personal finance","pageScore":0.01531189400702715},{"category":"personal finance-tax","pageScore":0.006849104072898626},{"category":"pets-cats","pageScore":0.007921791635453701},{"category":"real estate-mortgages","pageScore":0.007218123413622379},{"category":"real estate-real estate","pageScore":0.008489524014294148},{"category":"science-astronomy","pageScore":0.009692375548183918},{"category":"science-biology","pageScore":0.008079459890723229},{"category":"science-economics","pageScore":0.009156853891909123},{"category":"science-geology","pageScore":0.007170082535594702},{"category":"science-science","pageScore":0.00769434729591012},{"category":"sports-basketball","pageScore":0.009629948996007443},{"category":"sports-climbing","pageScore":0.0074807642959058289},{"category":"sports-cricket","pageScore":0.0076187592931091789},{"category":"sports-fishing","pageScore":0.008629723452031613},{"category":"sports-hockey","pageScore":0.007721950300037861},{"category":"sports-snowboarding","pageScore":0.0077972798608243469},{"category":"sports-sports","pageScore":0.011989245191216469},{"category":"sports-tennis","pageScore":0.007571316324174404},{"category":"sports-wrestling","pageScore":0.007291065063327551},{"category":"technology & computing-apple","pageScore":0.013022327795624733},{"category":"technology & computing-software","pageScore":0.011717082001268864},{"category":"technology & computing-unix","pageScore":0.07218202948570252},{"category":"technology & computing-windows","pageScore":0.009065560065209866},{"category":"weather-weather","pageScore":0.007231561001390219}]},{"pageProbabilities":[{"category":"architecture-architecture","pageScore":0.010663419030606747},{"category":"arts & entertainment-arts & entertainment","pageScore":0.007452860940247774},{"category":"arts & entertainment-design","pageScore":0.00946059636771679},{"category":"arts & entertainment-film","pageScore":0.007866622880101204},{"category":"arts & entertainment-literature","pageScore":0.008533122017979622},{"category":"business-business","pageScore":0.010438821278512478},{"category":"business-energy","pageScore":0.007745790760964155},{"category":"business-marketing","pageScore":0.009756538085639477},{"category":"cell phones-cell phones","pageScore":0.008917069993913174},{"category":"fashion-clothing","pageScore":0.006789426784962416},{"category":"folklore-astrology","pageScore":0.0072112176567316059},{"category":"folklore-paranormal phenomena","pageScore":0.008682048879563809},{"category":"food & drink-beer","pageScore":0.007441094145178795},{"category":"food & drink-cooking","pageScore":0.008447554893791676},{"category":"food & drink-vegan","pageScore":0.007444251794368029},{"category":"health & fitness-alternative medicine","pageScore":0.007157527841627598},{"category":"health & fitness-exercise","pageScore":0.010043740272521973},{"category":"health & fitness-sex","pageScore":0.00683544622734189},{"category":"history-archaeology","pageScore":0.008008942008018494},{"category":"history-history","pageScore":0.007581331767141819},{"category":"hobbies & interests-arts & crafts","pageScore":0.009757441468536854},{"category":"hobbies & interests-coins","pageScore":0.010205479338765145},{"category":"hobbies & interests-gambling","pageScore":0.007008743472397327},{"category":"hobbies & interests-horse racing","pageScore":0.007671969942748547},{"category":"hobbies & interests-needlework","pageScore":0.008056028746068478},{"category":"hobbies & interests-photography","pageScore":0.006800234783440828},{"category":"hobbies & interests-writing","pageScore":0.0071760183200240139},{"category":"home-garden","pageScore":0.010561102069914341},{"category":"home-home","pageScore":0.01134837418794632},{"category":"home-interior design","pageScore":0.014571985229849816},{"category":"military-military","pageScore":0.007764331065118313},{"category":"personal finance-credit & debt & loans","pageScore":0.012580132111907006},{"category":"personal finance-insurance","pageScore":0.00856517069041729},{"category":"personal finance-personal finance","pageScore":0.014102553017437458},{"category":"personal finance-retirement planning","pageScore":0.011182154528796673},{"category":"personal finance-tax","pageScore":0.007146195508539677},{"category":"real estate-real estate","pageScore":0.009525544941425324},{"category":"science-astronomy","pageScore":0.007812004070729017},{"category":"science-biology","pageScore":0.009636830538511277},{"category":"science-economics","pageScore":0.014292005449533463},{"category":"science-mathematics","pageScore":0.008016557432711125},{"category":"science-palaeontology","pageScore":0.008474347181618214},{"category":"science-science","pageScore":0.010102168656885624},{"category":"sports-baseball","pageScore":0.006997967138886452},{"category":"sports-fishing","pageScore":0.007804680150002241},{"category":"sports-jogging","pageScore":0.007243323139846325},{"category":"sports-soccer","pageScore":0.006873568054288626},{"category":"sports-sports","pageScore":0.008396070450544358},{"category":"sports-yoga","pageScore":0.007910885848104954},{"category":"technology & computing-apple","pageScore":0.010456928052008152},{"category":"technology & computing-freeware","pageScore":0.006804196629673243},{"category":"technology & computing-programming","pageScore":0.015553813427686692},{"category":"technology & computing-software","pageScore":0.008275683037936688},{"category":"technology & computing-technology & computing","pageScore":0.013762008398771286},{"category":"technology & computing-unix","pageScore":0.0140514662489295},{"category":"travel-adventure travel","pageScore":0.009901399724185467},{"category":"travel-travel","pageScore":0.006778400391340256},{"category":"weather-weather","pageScore":0.006908775772899389}]},{"pageProbabilities":[{"category":"architecture-architecture","pageScore":0.010663419030606747},{"category":"arts & entertainment-arts & entertainment","pageScore":0.007452860940247774},{"category":"arts & entertainment-design","pageScore":0.00946059636771679},{"category":"arts & entertainment-film","pageScore":0.007866622880101204},{"category":"arts & entertainment-literature","pageScore":0.008533122017979622},{"category":"business-business","pageScore":0.010438821278512478},{"category":"business-energy","pageScore":0.007745790760964155},{"category":"business-marketing","pageScore":0.009756538085639477},{"category":"cell phones-cell phones","pageScore":0.008917069993913174},{"category":"fashion-clothing","pageScore":0.006789426784962416},{"category":"folklore-astrology","pageScore":0.0072112176567316059},{"category":"folklore-paranormal phenomena","pageScore":0.008682048879563809},{"category":"food & drink-beer","pageScore":0.007441094145178795},{"category":"food & drink-cooking","pageScore":0.008447554893791676},{"category":"food & drink-vegan","pageScore":0.007444251794368029},{"category":"health & fitness-alternative medicine","pageScore":0.007157527841627598},{"category":"health & fitness-exercise","pageScore":0.010043740272521973},{"category":"health & fitness-sex","pageScore":0.00683544622734189},{"category":"history-archaeology","pageScore":0.008008942008018494},{"category":"history-history","pageScore":0.007581331767141819},{"category":"hobbies & interests-arts & crafts","pageScore":0.009757441468536854},{"category":"hobbies & interests-coins","pageScore":0.010205479338765145},{"category":"hobbies & interests-gambling","pageScore":0.007008743472397327},{"category":"hobbies & interests-horse racing","pageScore":0.007671969942748547},{"category":"hobbies & interests-needlework","pageScore":0.008056028746068478},{"category":"hobbies & interests-photography","pageScore":0.006800234783440828},{"category":"hobbies & interests-writing","pageScore":0.0071760183200240139},{"category":"home-garden","pageScore":0.010561102069914341},{"category":"home-home","pageScore":0.01134837418794632},{"category":"home-interior design","pageScore":0.014571985229849816},{"category":"military-military","pageScore":0.007764331065118313},{"category":"personal finance-credit & debt & loans","pageScore":0.012580132111907006},{"category":"personal finance-insurance","pageScore":0.00856517069041729},{"category":"personal finance-personal finance","pageScore":0.014102553017437458},{"category":"personal finance-retirement planning","pageScore":0.011182154528796673},{"category":"personal finance-tax","pageScore":0.007146195508539677},{"category":"real estate-real estate","pageScore":0.009525544941425324},{"category":"science-astronomy","pageScore":0.007812004070729017},{"category":"science-biology","pageScore":0.009636830538511277},{"category":"science-economics","pageScore":0.014292005449533463},{"category":"science-mathematics","pageScore":0.008016557432711125},{"category":"science-palaeontology","pageScore":0.008474347181618214},{"category":"science-science","pageScore":0.010102168656885624},{"category":"sports-baseball","pageScore":0.006997967138886452},{"category":"sports-fishing","pageScore":0.007804680150002241},{"category":"sports-jogging","pageScore":0.007243323139846325},{"category":"sports-soccer","pageScore":0.006873568054288626},{"category":"sports-sports","pageScore":0.008396070450544358},{"category":"sports-yoga","pageScore":0.007910885848104954},{"category":"technology & computing-apple","pageScore":0.010456928052008152},{"category":"technology & computing-freeware","pageScore":0.006804196629673243},{"category":"technology & computing-programming","pageScore":0.015553813427686692},{"category":"technology & computing-software","pageScore":0.008275683037936688},{"category":"technology & computing-technology & computing","pageScore":0.013762008398771286},{"category":"technology & computing-unix","pageScore":0.0140514662489295},{"category":"travel-adventure travel","pageScore":0.009901399724185467},{"category":"travel-travel","pageScore":0.006778400391340256},{"category":"weather-weather","pageScore":0.006908775772899389}]}],"version_code":""}